midigen/__init__.py
midigen/channel_pool.py
midigen/chord.py
midigen/compiler/__init__.py
midigen/compiler/midi_compiler.py
midigen/drums.py
midigen/instruments.py
midigen/key.py
midigen/melody.py
midigen/midigen.py
midigen/note.py
midigen/roman.py
midigen/scale.py
midigen/section.py
midigen/song.py
midigen/tests/__init__.py
midigen/tests/test_channel_pool.py
midigen/tests/test_chord.py
midigen/tests/test_drums.py
midigen/tests/test_golden_master.py
midigen/tests/test_integration.py
midigen/tests/test_key.py
midigen/tests/test_melody.py
midigen/tests/test_midigen.py
midigen/tests/test_note.py
midigen/tests/test_roman.py
midigen/tests/test_scale.py
midigen/tests/test_song.py
midigen/tests/test_time_utils.py
midigen/tests/test_track.py
midigen/time_utils.py
midigen/track.py
midigen_lib-1.0.0.dist-info/METADATA
midigen_lib-1.0.0.dist-info/WHEEL
midigen_lib-1.0.0.dist-info/licenses/LICENSE
midigen_lib-1.0.0.dist-info/RECORD
