Metadata-Version: 2.4
Name: midigen-lib
Version: 1.0.0
Summary: High-level, theory-powered MIDI generation library
License: GPL-3.0-only
License-File: LICENSE
Keywords: midi,music-generation,mido,music-theory
Author: cainky
Author-email: kylecain.me@gmail.com
Requires-Python: >=3.10,<4.0
Classifier: License :: OSI Approved :: GNU General Public License v3 (GPLv3)
Classifier: Programming Language :: Python :: 3
Classifier: Programming Language :: Python :: 3.10
Classifier: Programming Language :: Python :: 3.11
Classifier: Programming Language :: Python :: 3.12
Classifier: Programming Language :: Python :: 3.13
Classifier: Programming Language :: Python :: 3.14
Requires-Dist: mido (>=1.3.2,<2.0.0)
Project-URL: Repository, https://github.com/cainky/midigen
